siibra_toolbox_neuroimaging/__init__.py
siibra_toolbox_neuroimaging/assignment.py
siibra_toolbox_neuroimaging/cli.py
siibra_toolbox_neuroimaging-0.2a2.dist-info/LICENSE
siibra_toolbox_neuroimaging-0.2a2.dist-info/METADATA
siibra_toolbox_neuroimaging-0.2a2.dist-info/WHEEL
siibra_toolbox_neuroimaging-0.2a2.dist-info/entry_points.txt
siibra_toolbox_neuroimaging-0.2a2.dist-info/top_level.txt
siibra_toolbox_neuroimaging-0.2a2.dist-info/RECORD
