Metadata-Version: 2.1
Name: siibra-toolbox-neuroimaging
Version: 0.2a2
Summary: siibra-toolbox-neuroimaging - siibra toolbox for assignment of neuroimaging signals to brain regions
Home-page: https://github.com/FZJ-INM1-BDA/siibra-toolbox-neuroimaging
Author: Big Data Analytics Group, Institute of Neuroscience and Medicint (INM-1), Forschungszentrum Julich
Author-email: inm1-bda@fz-juelich.de
Classifier: Development Status :: 2 - Pre-Alpha
Classifier: Programming Language :: Python :: 3
Classifier: Operating System :: OS Independent
Classifier: Intended Audience :: Developers
Requires-Python: >=3.6
License-File: LICENSE
Requires-Dist: siibra (>=0.3a17)
Requires-Dist: siibra-cli (>=0.2a0)
Requires-Dist: matplotlib (>=3.3)
Requires-Dist: fpdf
